fireworks/__init__.py
fireworks/fw_config.py
fireworks/core/__init__.py
fireworks/core/firework.py
fireworks/core/fworker.py
fireworks/core/launchpad.py
fireworks/core/rocket.py
fireworks/core/rocket_launcher.py
fireworks/core/tests/__init__.py
fireworks/core/tests/tasks.py
fireworks/core/tests/test_firework.py
fireworks/core/tests/test_launchpad.py
fireworks/core/tests/test_rocket.py
fireworks/core/tests/test_tracker.py
fireworks/examples/__init__.py
fireworks/examples/custom_firetasks/__init__.py
fireworks/examples/custom_firetasks/hello_world/__init__.py
fireworks/examples/custom_firetasks/hello_world/hello_world_run.py
fireworks/examples/custom_firetasks/hello_world/hello_world_task.py
fireworks/examples/custom_firetasks/merge_task/__init__.py
fireworks/examples/custom_firetasks/merge_task/merge_task.py
fireworks/examples/tutorial_examples/__init__.py
fireworks/examples/tutorial_examples/dynamic_wf1.py
fireworks/examples/tutorial_examples/dynamic_wf2.py
fireworks/examples/tutorial_examples/firetasks.py
fireworks/examples/tutorial_examples/introduction.py
fireworks/examples/tutorial_examples/workflows.py
fireworks/features/__init__.py
fireworks/features/background_task.py
fireworks/features/dupefinder.py
fireworks/features/fw_report.py
fireworks/features/introspect.py
fireworks/features/multi_launcher.py
fireworks/features/stats.py
fireworks/features/tests/__init__.py
fireworks/features/tests/test_introspect.py
fireworks/flask_site/__init__.py
fireworks/flask_site/app.py
fireworks/flask_site/gunicorn.py
fireworks/flask_site/helpers.py
fireworks/flask_site/util.py
fireworks/flask_site/static/css/bootstrap.css
fireworks/flask_site/static/css/cytoscape.js-panzoom.css
fireworks/flask_site/static/css/flat-ui.css
fireworks/flask_site/static/css/jquery.jsonview.css
fireworks/flask_site/static/css/styles.css
fireworks/flask_site/static/images/fw-logo.png
fireworks/flask_site/static/js/cytoscape-panzoom.js
fireworks/flask_site/static/js/cytoscape.min.js
fireworks-2.0.8.dist-info/licenses/LICENSE
fireworks-2.0.8.dist-info/METADATA
fireworks-2.0.8.dist-info/WHEEL
fireworks-2.0.8.dist-info/entry_points.txt
fireworks-2.0.8.dist-info/top_level.txt
fireworks-2.0.8.dist-info/RECORD
